inboxkitten/__init__.py
inboxkitten-0.0.9.dist-info/LICENSES.txt
inboxkitten-0.0.9.dist-info/METADATA
inboxkitten-0.0.9.dist-info/WHEEL
inboxkitten-0.0.9.dist-info/top_level.txt
inboxkitten-0.0.9.dist-info/RECORD
