Metadata-Version: 2.1
Name: inboxkitten
Version: 0.0.9
Summary: This package can make temp email from https://inboxkitten.com/
Home-page: https://github.com/TeaByte/inboxkitten/
Author: 01270
Author-email: yazanemails@gmail.com
License: UNKNOWN
Project-URL: Source, https://github.com/TeaByte/inboxkitten/
Project-URL: Bug Reports, https://github.com/TeaByte/inboxkitten/issues
Project-URL: Documentation, https://github.com/TeaByte/inboxkitten/
Keywords: inboxkitten,inbox,kitten,temp mail,temp,temp email,email,emails
Platform: UNKNOWN
Classifier: Development Status :: 1 - Planning
Classifier: Intended Audience :: Developers
Classifier: Programming Language :: Python :: 3
Classifier: Operating System :: Unix
Classifier: Operating System :: MacOS :: MacOS X
Classifier: Operating System :: Microsoft :: Windows
License-File: LICENSES.txt
Requires-Dist: requests
